multi_language_sentiment.py
multi_language_sentiment-0.1.0.dist-info/LICENSE
multi_language_sentiment-0.1.0.dist-info/WHEEL
multi_language_sentiment-0.1.0.dist-info/METADATA
multi_language_sentiment-0.1.0.dist-info/RECORD
