Metadata-Version: 2.1
Name: multi_language_sentiment
Version: 0.1.0
Summary: Sentiment analysis pipeline for texts in multiple languages.
Author-email: Jarno Rantaharju <jarno.rantaharju@aalto.fi>
Classifier: License :: OSI Approved :: MIT License
Requires-Dist: transformers
Requires-Dist: torch
Requires-Dist: lingua-language-detector
Requires-Dist: pytest ; extra == "test"
Project-URL: Repository, https://github.com/rantahar/google_takeout_email
Provides-Extra: test
